{
  "Version": "1.22.1007.1",
  "Description": "測試用設定",
  "ProcessPriority": "Normal",
  "Big5EncodingCodePage": 950,
  "ScreenshotFolderPath": "Screenshot",
  "ShowDataGrid": true,
  "DataGridAppLogRowsMax": 500,
  "TimerIntervalBackground": 30,
  "TimerIntervalUI1": 300,
  "TimerIntervalUI2": 35000,
  "HolidayFilePath": "holidaySchedule_{yyy}.csv",
  "HolidayFileKeywords1": [
    "月",
    "日"
  ],
  "HolidayFileKeywords2": [
    "放假",
    "無交易",
    "補假"
  ],
  "AutoRunInTradeDay": true,
  "AutoRunInHoliday": false,
  "CapitalLogPathSuffix": "_CapitalLog",
  "LiveMode": false,
  "LiveModeAPIReply": [
    "UserID",
    "Message"
  ],
  "LiveModeAppLog": [],
  "LiveModeTriggerRule": [
    "ColumnName",
    "ColumnProperty",
    "ColumnValue",
    "TargetValue",
    "Symbol2Setting"
  ],
  "LiveModeStrategyRule": [
    "FullAccount",
    "BSEnum",
    "MarketPrice",
    "OrderPriceBefore",
    "OrderPriceAfter",
    "OrderQty",
    "BestClosePrice",
    "StopLossBefore",
    "StopLossAfter",
    "StopWinPriceABefore",
    "StopWinPriceAAfter",
    "StopWin1Before",
    "StopWin1After",
    "StopWin2Before",
    "StopWin2After",
    "DealPrice",
    "UnclosedQty",
    "AccountsWinLossClose"
  ],
  "LiveModeOrderDetail": [
    "FullAccount",
    "BSEnum",
    "MarketPrice",
    "OrderPriceBefore",
    "OrderPriceAfter",
    "OrderQty",
    "OrderReport",
    "DealPrice",
    "DealQty",
    "DealReport",
    "UnclosedQty"
  ],
  "LiveModeOpenInterest": [
    "Account",
    "BSEnum",
    "MarketPrice",
    "AveragePrice",
    "Quantity"
  ],
  "LiveModeFuturesRights": [
    "UserID",
    "Account"
  ],
  "MarketStart": [
    "15:00:00",
    "08:45:00"
  ],
  "MarketClose": [
    "05:00:00",
    "13:45:00"
  ],
  "FuturesLastTradeWeek": 3,
  "FuturesLastTradeDay": "Wednesday",
  "DayToChangeFutures": -1,
  "QuoteMarkets": [],
  "QuoteRequest": [
    "TSEA",
    "0050",
    "00632R",
    "UN2312",
    "TX03",
    "MTX03",
    "TXO16300L3",
    "TXO16500L3",
    "TXO16700L3",
    "TXO16900L3",
    "TXO17100L3",
    "TXO17300L3",
    "TXO17500L3",
    "TXO16300X3",
    "TXO16500X3",
    "TXO16700X3",
    "TXO16900X3",
    "TXO17100X3",
    "TXO17300X3",
    "TXO17500X3",
  ],
  "QuoteLive": [
    "2330",
    "UD12",
    "TX12",
    "MTX12"
  ],
  "QuoteFolderPath": "QuoteData",
  "QuoteFileOpenPrefix": "Open_",
  "QuoteFileClosePrefix": "Last_",
  "QuoteFileRecoverPrefix": "Recover_",
  "QuoteSaveInterval": 45,
  "OpenInterestInterval": 8,
  "FuturesRightsInterval": 28,
  "OrderOpenCloseInterval": 100,
  "OrderLimitStopWinInterval": 50,
  "OrderCancelInterval": 500,
  "OrderMaxQty": 50,
  "OrderMaxCount": 50,
  "TriggerFolderPath": "TriggerData",
  "TriggerFileLoadFormat": "R*{DayNight}*.csv",
  "TriggerFileSaveFormat": "MMdd_HHmm",
  "TriggerReadAndCancel": "ZT",
  "StrategyFolderPath": "StrategyData",
  "StrategyFileLoadFormat": "R*{Holiday}_{DayNight}*.csv",
  "StrategyFileSaveFormat": "MMdd_HHmm",
  "StrategyNotForOpenInterest": "ZS",
  "StrategyFromOpenInterest": false,
  "StrategyStopWinProfit": 500,
  "StrategyStopWinOffset": -1,
  "SentOrderFolderPath": "SentOrder",
  "SentOrderFileFormat": "yyMMdd_HHmmss_ffffff",
  "SendRealOrder": false,
}
